AUTHORS.txt
CHANGES.txt
LICENSE.txt
MANIFEST.in
README.rst
requirements.txt
setup.py
VCC.egg-info/PKG-INFO
VCC.egg-info/SOURCES.txt
VCC.egg-info/dependency_links.txt
VCC.egg-info/entry_points.txt
VCC.egg-info/requires.txt
VCC.egg-info/top_level.txt
vcc/__init__.py
vcc/consumer.py
vcc/counters.py
vcc/runner.py
vcc/ui.py
vcc/helpers/__init__.py
vcc/helpers/log.py
vcc/helpers/varnish.py