Metadata-Version: 1.1
Name: VCC
Version: 0.1
Summary: Varnish Custom Counters (VCC) allows aggregation of custom log entries extracted from Varnish shared memory log.
Home-page: https://github.com/carlosabalde/vcc
Author: Carlos Abalde
Author-email: carlos.abalde@gmail.com
License: GPL
Platform: UNKNOWN
Classifier: Intended Audience :: System Administrators
Classifier: Operating System :: OS Independent
